soxy/__init__.py
soxy/__main__.py
soxy/_config.py
soxy/_errors.py
soxy/_logger.py
soxy/_packages.py
soxy/_proxy.py
soxy/_ruleset.py
soxy/_session.py
soxy/_socks.py
soxy/_tcp.py
soxy/_types.py
soxy/_utils.py
soxy/_wrappers.py
soxy/py.typed
soxyproxy-0.10.0.dist-info/METADATA
soxyproxy-0.10.0.dist-info/WHEEL
soxyproxy-0.10.0.dist-info/entry_points.txt
soxyproxy-0.10.0.dist-info/licenses/LICENSE
soxyproxy-0.10.0.dist-info/RECORD
