Metadata-Version: 2.4
Name: soxyproxy
Version: 0.10.0
Summary: Add your description here
Project-URL: Homepage, https://github.com/shpaker/soxyproxy/
Author-email: Aleksandr Shpak <shpaker@gmail.com>
License-Expression: GPL-3.0
License-File: LICENSE
Keywords: proxy,socks,socks4,socks4a,socks5,socks5h
Classifier: Development Status :: 3 - Alpha
Classifier: Intended Audience :: Developers
Classifier: License :: OSI Approved :: GNU General Public License v3 (GPLv3)
Classifier: Operating System :: OS Independent
Classifier: Programming Language :: Python :: 3
Classifier: Programming Language :: Python :: 3 :: Only
Classifier: Programming Language :: Python :: 3.14
Classifier: Topic :: Internet :: Proxy Servers
Classifier: Topic :: Software Development :: Libraries :: Python Modules
Classifier: Typing :: Typed
Requires-Python: >=3.14
